<?xml version="1.0"?>
<MethodSetup Method="Cuts::CutsSA">
  <GeneralInfo>
    <Info name="TMVA Release" value="4.2.1 [262657]"/>
    <Info name="ROOT Release" value="6.12/07 [396295]"/>
    <Info name="Creator" value="gwangjun"/>
    <Info name="Date" value="Mon Jun  3 22:44:42 2019"/>
    <Info name="Host" value="Linux vocms0315.cern.ch 2.6.32-696.30.1.el6.x86_64 #1 SMP Tue May 22 06:09:36 CEST 2018 x86_64 x86_64 x86_64 GNU/Linux"/>
    <Info name="Dir" value="/afs/lns.mit.edu/user/gwangjun/CMSSW_10_3_2/src/BmesonRun2018/tmva/train"/>
    <Info name="Training events" value="205954"/>
    <Info name="TrainingTime" value="2.53967600e+02"/>
    <Info name="AnalysisType" value="Classification"/>
  </GeneralInfo>
  <Options>
    <Option name="V" modified="Yes">False</Option>
    <Option name="VerbosityLevel" modified="No">Default</Option>
    <Option name="VarTransform" modified="No">None</Option>
    <Option name="H" modified="Yes">False</Option>
    <Option name="CreateMVAPdfs" modified="No">False</Option>
    <Option name="IgnoreNegWeightsInTraining" modified="No">False</Option>
    <Option name="FitMethod" modified="Yes">SA</Option>
    <Option name="EffMethod" modified="Yes">EffSel</Option>
    <Option name="CutRangeMin" size="6" modified="No">-1.000000e+00 -1.000000e+00 -1.000000e+00 -1.000000e+00 -1.000000e+00 -1.000000e+00</Option>
    <Option name="CutRangeMax" size="6" modified="No">-1.000000e+00 -1.000000e+00 -1.000000e+00 -1.000000e+00 -1.000000e+00 -1.000000e+00</Option>
    <Option name="VarProp" size="6" modified="No">FMax FMax FMax FMax FMax FMax</Option>
  </Options>
  <Variables NVar="6">
    <Variable VarIndex="0" Expression="TMath::Abs(BsvpvDistance/BsvpvDisErr)" Label="dls3D" Title="dls3D" Unit="" Internal="dls3D" Type="F" Min="2.00000405e+00" Max="1.45694617e+03"/>
    <Variable VarIndex="1" Expression="TMath::Cos(Bdtheta)" Label="costheta" Title="costheta" Unit="" Internal="costheta" Type="F" Min="-1.00000000e+00" Max="1.00000000e+00"/>
    <Variable VarIndex="2" Expression="TMath::Abs(Btrk1Dxy1/Btrk1DxyError1)" Label="Btrk1Dxysig" Title="Btrk1Dxysig" Unit="" Internal="Btrk1Dxysig" Type="F" Min="4.25744111e-06" Max="3.78855553e+01"/>
    <Variable VarIndex="3" Expression="TMath::Abs(Btrk1Dz1/Btrk1DzError1)" Label="Btrk1Dzsig" Title="Btrk1Dzsig" Unit="" Internal="Btrk1Dzsig" Type="F" Min="3.77709080e-06" Max="1.55716064e+03"/>
    <Variable VarIndex="4" Expression="Btrk1Pt" Label="Btrk1Pt" Title="Btrk1Pt" Unit="" Internal="Btrk1Pt" Type="F" Min="9.00009394e-01" Max="4.68924141e+00"/>
    <Variable VarIndex="5" Expression="Bchi2cl" Label="Bchi2cl" Title="Bchi2cl" Unit="" Internal="Bchi2cl" Type="F" Min="5.00020087e-02" Max="9.99987423e-01"/>
  </Variables>
  <Spectators NSpec="0"/>
  <Classes NClass="2">
    <Class Name="Signal" Index="0"/>
    <Class Name="Background" Index="1"/>
  </Classes>
  <Transformations NTransformations="0"/>
  <MVAPdfs/>
  <Weights OptimisationMethod="0" FitMethod="2" nbins="100">
    <!--Below are the optimised cuts for 6 variables: Format: ibin(hist) effS effB cutMin[ivar=0] cutMax[ivar=0] ... cutMin[ivar=n-1] cutMax[ivar=n-1]-->
    <Bin ibin="1" effS="0.0000000000000000e+00" effB="0.0000000000000000e+00">
      <Cuts cutMin_0="7.9388797144752084e+02" cutMax_0="1.0000000000000000e+30" cutMin_1="-4.5212645924650130e-01" cutMax_1="1.0000000000000000e+30" cutMin_2="1.6025893298429200e+01" cutMax_2="1.0000000000000000e+30" cutMin_3="1.3261895878949074e+03" cutMax_3="1.0000000000000000e+30" cutMin_4="8.8035555379500907e-01" cutMax_4="1.0000000000000000e+30" cutMin_5="1.5830082309379639e-01" cutMax_5="1.0000000000000000e+30"/>
    </Bin>
    <Bin ibin="2" effS="1.0000000000000000e-02" effB="0.0000000000000000e+00">
      <Cuts cutMin_0="4.1407185526458761e+01" cutMax_0="1.0000000000000000e+30" cutMin_1="-4.5509724028668225e-01" cutMax_1="1.0000000000000000e+30" cutMin_2="3.2833697882846340e+00" cutMax_2="1.0000000000000000e+30" cutMin_3="3.8088854081183669e+01" cutMax_3="1.0000000000000000e+30" cutMin_4="9.1811489398204016e-01" cutMax_4="1.0000000000000000e+30" cutMin_5="4.8252216974282874e-01" cutMax_5="1.0000000000000000e+30"/>
    </Bin>
    <Bin ibin="3" effS="2.0000000000000000e-02" effB="0.0000000000000000e+00">
      <Cuts cutMin_0="3.2847048175130240e+00" cutMax_0="1.0000000000000000e+30" cutMin_1="5.6890095056135648e-01" cutMax_1="1.0000000000000000e+30" cutMin_2="1.0601958181731961e+01" cutMax_2="1.0000000000000000e+30" cutMin_3="1.8300951967731301e+01" cutMax_3="1.0000000000000000e+30" cutMin_4="1.0495219617201414e+00" cutMax_4="1.0000000000000000e+30" cutMin_5="6.9624378233858242e-01" cutMax_5="1.0000000000000000e+30"/>
    </Bin>
    <Bin ibin="4" effS="2.9999999999999999e-02" effB="0.0000000000000000e+00">
      <Cuts cutMin_0="6.7183826991370683e+00" cutMax_0="1.0000000000000000e+30" cutMin_1="7.2090121486153258e-01" cutMax_1="1.0000000000000000e+30" cutMin_2="1.2116398579617604e+01" cutMax_2="1.0000000000000000e+30" cutMin_3="-5.0053044734405443e+00" cutMax_3="1.0000000000000000e+30" cutMin_4="1.4114986975397217e+00" cutMax_4="1.0000000000000000e+30" cutMin_5="3.8851872960136147e-01" cutMax_5="1.0000000000000000e+30"/>
    </Bin>
    <Bin ibin="5" effS="4.0000000000000001e-02" effB="0.0000000000000000e+00">
      <Cuts cutMin_0="9.8681315323867977e+00" cutMax_0="1.0000000000000000e+30" cutMin_1="1.0203964898391749e-01" cutMax_1="1.0000000000000000e+30" cutMin_2="2.5979498682845459e+00" cutMax_2="1.0000000000000000e+30" cutMin_3="1.0220674643707385e+01" cutMax_3="1.0000000000000000e+30" cutMin_4="1.7722519039520384e+00" cutMax_4="1.0000000000000000e+30" cutMin_5="6.0381563826515094e-01" cutMax_5="1.0000000000000000e+30"/>
    </Bin>
    <Bin ibin="6" effS="5.0000000000000003e-02" effB="0.0000000000000000e+00">
      <Cuts cutMin_0="3.8108962791136562e+01" cutMax_0="1.0000000000000000e+30" cutMin_1="7.2586309151252149e-01" cutMax_1="1.0000000000000000e+30" cutMin_2="1.4619479797553252e+01" cutMax_2="1.0000000000000000e+30" cutMin_3="-9.6257919605277227e+00" cutMax_3="1.0000000000000000e+30" cutMin_4="1.2444329702671972e+00" cutMax_4="1.0000000000000000e+30" cutMin_5="6.7586746140821752e-01" cutMax_5="1.0000000000000000e+30"/>
    </Bin>
    <Bin ibin="7" effS="5.9999999999999998e-02" effB="0.0000000000000000e+00">
      <Cuts cutMin_0="2.9871714692852166e+01" cutMax_0="1.0000000000000000e+30" cutMin_1="-1.7852915941287695e-01" cutMax_1="1.0000000000000000e+30" cutMin_2="2.4579241838444514e+00" cutMax_2="1.0000000000000000e+30" cutMin_3="2.9882974586533422e+01" cutMax_3="1.0000000000000000e+30" cutMin_4="1.1884494777022723e+00" cutMax_4="1.0000000000000000e+30" cutMin_5="1.0329919981185734e-01" cutMax_5="1.0000000000000000e+30"/>
    </Bin>
    <Bin ibin="8" effS="7.0000000000000007e-02" effB="0.0000000000000000e+00">
      <Cuts cutMin_0="-7.1010737794878709e-01" cutMax_0="1.0000000000000000e+30" cutMin_1="-5.3090518019805166e-01" cutMax_1="1.0000000000000000e+30" cutMin_2="2.6713723503487010e+00" cutMax_2="1.0000000000000000e+30" cutMin_3="2.8155457902986171e+01" cutMax_3="1.0000000000000000e+30" cutMin_4="1.1864727564568078e+00" cutMax_4="1.0000000000000000e+30" cutMin_5="6.4796458464779452e-02" cutMax_5="1.0000000000000000e+30"/>
    </Bin>
    <Bin ibin="9" effS="8.0000000000000002e-02" effB="4.8570332182862330e-06">
      <Cuts cutMin_0="2.0306286819648030e+01" cutMax_0="1.0000000000000000e+30" cutMin_1="-5.5619745311537727e-01" cutMax_1="1.0000000000000000e+30" cutMin_2="3.3355760010982638e+00" cutMax_2="1.0000000000000000e+30" cutMin_3="2.3941289166567547e+01" cutMax_3="1.0000000000000000e+30" cutMin_4="1.1300797856081704e+00" cutMax_4="1.0000000000000000e+30" cutMin_5="1.1323450496989773e-01" cutMax_5="1.0000000000000000e+30"/>
    </Bin>
    <Bin ibin="10" effS="8.9999999999999997e-02" effB="4.8570332182862330e-06">
      <Cuts cutMin_0="1.3505718626079766e+01" cutMax_0="1.0000000000000000e+30" cutMin_1="7.6566863785256634e-01" cutMax_1="1.0000000000000000e+30" cutMin_2="1.0631600440986743e+01" cutMax_2="1.0000000000000000e+30" cutMin_3="-6.6439029690664739e+00" cutMax_3="1.0000000000000000e+30" cutMin_4="1.1468052160336479e+00" cutMax_4="1.0000000000000000e+30" cutMin_5="8.0931899916359407e-01" cutMax_5="1.0000000000000000e+30"/>
    </Bin>
    <Bin ibin="11" effS="1.0000000000000001e-01" effB="4.8570332182862330e-06">
      <Cuts cutMin_0="1.2651944282031629e+01" cutMax_0="1.0000000000000000e+30" cutMin_1="-5.8963260491897007e-01" cutMax_1="1.0000000000000000e+30" cutMin_2="4.5515998654701511e+00" cutMax_2="1.0000000000000000e+30" cutMin_3="1.0766432297595848e+01" cutMax_3="1.0000000000000000e+30" cutMin_4="1.0318195522917806e+00" cutMax_4="1.0000000000000000e+30" cutMin_5="7.3367858290967514e-01" cutMax_5="1.0000000000000000e+30"/>
    </Bin>
    <Bin ibin="12" effS="1.1000000000000000e-01" effB="1.4571100109606050e-05">
      <Cuts cutMin_0="1.0189419340663356e+01" cutMax_0="1.0000000000000000e+30" cutMin_1="9.8339751540829745e-01" cutMax_1="1.0000000000000000e+30" cutMin_2="1.4696041578978813e+00" cutMax_2="1.0000000000000000e+30" cutMin_3="2.0928632725357723e+01" cutMax_3="1.0000000000000000e+30" cutMin_4="1.0362209611998889e+00" cutMax_4="1.0000000000000000e+30" cutMin_5="7.6243074653484677e-02" cutMax_5="1.0000000000000000e+30"/>
    </Bin>
    <Bin ibin="13" effS="1.2000000000000000e-01" effB="9.7140664365724660e-06">
      <Cuts cutMin_0="2.9163865811107069e+01" cutMax_0="1.0000000000000000e+30" cutMin_1="9.4515433788118253e-01" cutMax_1="1.0000000000000000e+30" cutMin_2="2.5300626012397447e+00" cutMax_2="1.0000000000000000e+30" cutMin_3="-7.9721153133776061e+00" cutMax_3="1.0000000000000000e+30" cutMin_4="1.2140321723548975e+00" cutMax_4="1.0000000000000000e+30" cutMin_5="1.1377389751859382e-01" cutMax_5="1.0000000000000000e+30"/>
    </Bin>
    <Bin ibin="14" effS="1.3000000000000000e-01" effB="9.7140664365724660e-06">
      <Cuts cutMin_0="2.6605850708686194e+01" cutMax_0="1.0000000000000000e+30" cutMin_1="9.8894810836683655e-01" cutMax_1="1.0000000000000000e+30" cutMin_2="3.5182348276601347e+00" cutMax_2="1.0000000000000000e+30" cutMin_3="-4.0387026639505290e+00" cutMax_3="1.0000000000000000e+30" cutMin_4="1.1563447758290855e+00" cutMax_4="1.0000000000000000e+30" cutMin_5="1.0411850934339022e-01" cutMax_5="1.0000000000000000e+30"/>
    </Bin>
    <Bin ibin="15" effS="1.4000000000000001e-01" effB="9.7140664365724660e-06">
      <Cuts cutMin_0="2.8341524010273652e+01" cutMax_0="1.0000000000000000e+30" cutMin_1="9.9189072209296436e-01" cutMax_1="1.0000000000000000e+30" cutMin_2="2.0670247998671085e+00" cutMax_2="1.0000000000000000e+30" cutMin_3="-4.9075516860672277e+00" cutMax_3="1.0000000000000000e+30" cutMin_4="1.0160214458395989e+00" cutMax_4="1.0000000000000000e+30" cutMin_5="5.5130430381934672e-02" cutMax_5="1.0000000000000000e+30"/>
    </Bin>
    <Bin ibin="16" effS="1.4999999999999999e-01" effB="2.9142200219212100e-05">
      <Cuts cutMin_0="-1.8348868532185585e+00" cutMax_0="1.0000000000000000e+30" cutMin_1="9.5038183410579691e-01" cutMax_1="1.0000000000000000e+30" cutMin_2="2.7498424545845772e+00" cutMax_2="1.0000000000000000e+30" cutMin_3="1.2570573716929882e+01" cutMax_3="1.0000000000000000e+30" cutMin_4="1.1526435907433659e+00" cutMax_4="1.0000000000000000e+30" cutMin_5="1.1562157474228062e-01" cutMax_5="1.0000000000000000e+30"/>
    </Bin>
    <Bin ibin="17" effS="1.6000000000000000e-01" effB="2.9142200219212100e-05">
      <Cuts cutMin_0="2.2664516866210302e+01" cutMax_0="1.0000000000000000e+30" cutMin_1="9.1830888888248974e-01" cutMax_1="1.0000000000000000e+30" cutMin_2="1.5023353399424544e+00" cutMax_2="1.0000000000000000e+30" cutMin_3="1.2989765088749728e+01" cutMax_3="1.0000000000000000e+30" cutMin_4="1.1661491324034656e+00" cutMax_4="1.0000000000000000e+30" cutMin_5="7.7015747869581375e-02" cutMax_5="1.0000000000000000e+30"/>
    </Bin>
    <Bin ibin="18" effS="1.7000000000000001e-01" effB="3.3999232982750982e-05">
      <Cuts cutMin_0="2.3246085765997570e+01" cutMax_0="1.0000000000000000e+30" cutMin_1="9.9528340721042152e-01" cutMax_1="1.0000000000000000e+30" cutMin_2="7.6450116489791864e-01" cutMax_2="1.0000000000000000e+30" cutMin_3="6.1102715152599760e+00" cutMax_3="1.0000000000000000e+30" cutMin_4="1.0933188254479000e+00" cutMax_4="1.0000000000000000e+30" cutMin_5="4.5800435489453326e-02" cutMax_5="1.0000000000000000e+30"/>
    </Bin>
    <Bin ibin="19" effS="1.7999999999999999e-01" effB="4.8570331273367628e-05">
      <Cuts cutMin_0="1.3184353631436704e+01" cutMax_0="1.0000000000000000e+30" cutMin_1="9.9935289964455121e-01" cutMax_1="1.0000000000000000e+30" cutMin_2="3.4209084807699446e+00" cutMax_2="1.0000000000000000e+30" cutMin_3="1.3240757150808182e+00" cutMax_3="1.0000000000000000e+30" cutMin_4="1.2234909376311138e+00" cutMax_4="1.0000000000000000e+30" cutMin_5="1.0248440078384927e-01" cutMax_5="1.0000000000000000e+30"/>
    </Bin>
    <Bin ibin="20" effS="1.9000000000000000e-01" effB="4.3713298509828746e-05">
      <Cuts cutMin_0="3.7244653497411315e+00" cutMax_0="1.0000000000000000e+30" cutMin_1="9.9615332815716107e-01" cutMax_1="1.0000000000000000e+30" cutMin_2="1.2732820700202776e+00" cutMax_2="1.0000000000000000e+30" cutMin_3="1.2366730253184572e+01" cutMax_3="1.0000000000000000e+30" cutMin_4="1.1282257844743298e+00" cutMax_4="1.0000000000000000e+30" cutMin_5="7.2583487362254936e-02" cutMax_5="1.0000000000000000e+30"/>
    </Bin>
    <Bin ibin="21" effS="2.0000000000000001e-01" effB="5.8284400438424200e-05">
      <Cuts cutMin_0="1.2342836839677679e+01" cutMax_0="1.0000000000000000e+30" cutMin_1="9.9495152733383796e-01" cutMax_1="1.0000000000000000e+30" cutMin_2="3.6876836338841206e+00" cutMax_2="1.0000000000000000e+30" cutMin_3="-1.2213209244967342e+01" cutMax_3="1.0000000000000000e+30" cutMin_4="1.2109537807699038e+00" cutMax_4="1.0000000000000000e+30" cutMin_5="2.0867048661657217e-01" cutMax_5="1.0000000000000000e+30"/>
    </Bin>
    <Bin ibin="22" effS="2.0999999999999999e-01" effB="7.2855495091062039e-05">
      <Cuts cutMin_0="1.1970324369784707e+01" cutMax_0="1.0000000000000000e+30" cutMin_1="9.9905078263169145e-01" cutMax_1="1.0000000000000000e+30" cutMin_2="-8.1737609794680255e-02" cutMax_2="1.0000000000000000e+30" cutMin_3="1.9688276182809687e+00" cutMax_3="1.0000000000000000e+30" cutMin_4="1.2434360723923796e+00" cutMax_4="1.0000000000000000e+30" cutMin_5="8.9970571111424452e-02" cutMax_5="1.0000000000000000e+30"/>
    </Bin>
    <Bin ibin="23" effS="2.2000000000000000e-01" effB="8.2569567894097418e-05">
      <Cuts cutMin_0="9.9328646316071882e+00" cutMax_0="1.0000000000000000e+30" cutMin_1="9.9199940060476255e-01" cutMax_1="1.0000000000000000e+30" cutMin_2="4.4070418057179657e+00" cutMax_2="1.0000000000000000e+30" cutMin_3="-6.0283137981274280e+00" cutMax_3="1.0000000000000000e+30" cutMin_4="1.0743714051294484e+00" cutMax_4="1.0000000000000000e+30" cutMin_5="2.1071355997740324e-01" cutMax_5="1.0000000000000000e+30"/>
    </Bin>
    <Bin ibin="24" effS="2.3000000000000001e-01" effB="1.3599693193100393e-04">
      <Cuts cutMin_0="1.0512670238329916e+01" cutMax_0="1.0000000000000000e+30" cutMin_1="9.1409105441235405e-01" cutMax_1="1.0000000000000000e+30" cutMin_2="1.5959456806441619e+00" cutMax_2="1.0000000000000000e+30" cutMin_3="3.6736145399647246e+00" cutMax_3="1.0000000000000000e+30" cutMin_4="1.2646688507367563e+00" cutMax_4="1.0000000000000000e+30" cutMin_5="2.7212270651057285e-01" cutMax_5="1.0000000000000000e+30"/>
    </Bin>
    <Bin ibin="25" effS="2.3999999999999999e-01" effB="7.2855495091062039e-05">
      <Cuts cutMin_0="1.1895390996172376e+01" cutMax_0="1.0000000000000000e+30" cutMin_1="9.9977145384607358e-01" cutMax_1="1.0000000000000000e+30" cutMin_2="3.6975549576513256e-01" cutMax_2="1.0000000000000000e+30" cutMin_3="1.2716418623899821e+00" cutMax_3="1.0000000000000000e+30" cutMin_4="1.0331144347577832e+00" cutMax_4="1.0000000000000000e+30" cutMin_5="4.1112982135328331e-02" cutMax_5="1.0000000000000000e+30"/>
    </Bin>
    <Bin ibin="26" effS="2.5000000000000000e-01" effB="8.7426597019657493e-05">
      <Cuts cutMin_0="1.0516114710674746e+01" cutMax_0="1.0000000000000000e+30" cutMin_1="9.9291417894147427e-01" cutMax_1="1.0000000000000000e+30" cutMin_2="1.4565803722767903e+00" cutMax_2="1.0000000000000000e+30" cutMin_3="4.2133559726635870e+00" cutMax_3="1.0000000000000000e+30" cutMin_4="1.0795622531329288e+00" cutMax_4="1.0000000000000000e+30" cutMin_5="2.6857152164777032e-01" cutMax_5="1.0000000000000000e+30"/>
    </Bin>
    <Bin ibin="27" effS="2.6000000000000001e-01" effB="2.9142200219212100e-05">
      <Cuts cutMin_0="1.3937913479921527e-01" cutMax_0="1.0000000000000000e+30" cutMin_1="9.9931077449117234e-01" cutMax_1="1.0000000000000000e+30" cutMin_2="3.7061836345717052e+00" cutMax_2="1.0000000000000000e+30" cutMin_3="-1.5041523821371687e+01" cutMax_3="1.0000000000000000e+30" cutMin_4="9.7500027785867327e-01" cutMax_4="1.0000000000000000e+30" cutMin_5="6.4277886786003946e-01" cutMax_5="1.0000000000000000e+30"/>
    </Bin>
    <Bin ibin="28" effS="2.7000000000000002e-01" effB="6.7998465965501964e-05">
      <Cuts cutMin_0="7.5658261126115960e+00" cutMax_0="1.0000000000000000e+30" cutMin_1="9.9919713865897553e-01" cutMax_1="1.0000000000000000e+30" cutMin_2="1.8617647713213132e+00" cutMax_2="1.0000000000000000e+30" cutMin_3="-3.9363875546479523e+00" cutMax_3="1.0000000000000000e+30" cutMin_4="9.9622821030647279e-01" cutMax_4="1.0000000000000000e+30" cutMin_5="3.9329714626959772e-01" cutMax_5="1.0000000000000000e+30"/>
    </Bin>
    <Bin ibin="29" effS="2.8000000000000003e-01" effB="3.3999232982750982e-05">
      <Cuts cutMin_0="1.4636594000179167e+01" cutMax_0="1.0000000000000000e+30" cutMin_1="5.0377391102488489e-01" cutMax_1="1.0000000000000000e+30" cutMin_2="4.7599092074317655e+00" cutMax_2="1.0000000000000000e+30" cutMin_3="-6.0865569227487164e+00" cutMax_3="1.0000000000000000e+30" cutMin_4="9.6878259759728425e-01" cutMax_4="1.0000000000000000e+30" cutMin_5="6.8737826026772353e-01" cutMax_5="1.0000000000000000e+30"/>
    </Bin>
    <Bin ibin="30" effS="2.8999999999999998e-01" effB="9.2283633421175182e-05">
      <Cuts cutMin_0="1.4618436666420926e+01" cutMax_0="1.0000000000000000e+30" cutMin_1="9.8724523217888627e-01" cutMax_1="1.0000000000000000e+30" cutMin_2="4.2713837249930586e+00" cutMax_2="1.0000000000000000e+30" cutMin_3="-4.8570181538023629e+00" cutMax_3="1.0000000000000000e+30" cutMin_4="9.6233591485542980e-01" cutMax_4="1.0000000000000000e+30" cutMin_5="1.4013680552444402e-01" cutMax_5="1.0000000000000000e+30"/>
    </Bin>
    <Bin ibin="31" effS="2.9999999999999999e-01" effB="5.3427364036906511e-05">
      <Cuts cutMin_0="1.3004670972411104e+01" cutMax_0="1.0000000000000000e+30" cutMin_1="9.9829996172363955e-01" cutMax_1="1.0000000000000000e+30" cutMin_2="9.8047420433181798e-01" cutMax_2="1.0000000000000000e+30" cutMin_3="-1.2248866243725438e+01" cutMax_3="1.0000000000000000e+30" cutMin_4="9.5860797135901898e-01" cutMax_4="1.0000000000000000e+30" cutMin_5="4.3968929048404887e-01" cutMax_5="1.0000000000000000e+30"/>
    </Bin>
    <Bin ibin="32" effS="3.1000000000000000e-01" effB="5.8284400438424200e-05">
      <Cuts cutMin_0="1.4032386416009087e+01" cutMax_0="1.0000000000000000e+30" cutMin_1="-8.9677687838739084e-02" cutMax_1="1.0000000000000000e+30" cutMin_2="3.0816703234468203e+00" cutMax_2="1.0000000000000000e+30" cutMin_3="-1.6324511211261661e-01" cutMax_3="1.0000000000000000e+30" cutMin_4="9.8593600120242209e-01" cutMax_4="1.0000000000000000e+30" cutMin_5="6.7743638147202034e-01" cutMax_5="1.0000000000000000e+30"/>
    </Bin>
    <Bin ibin="33" effS="3.2000000000000001e-01" effB="7.7712531492579728e-05">
      <Cuts cutMin_0="1.3671533325925907e+01" cutMax_0="1.0000000000000000e+30" cutMin_1="9.9291691256822023e-01" cutMax_1="1.0000000000000000e+30" cutMin_2="4.6865076645666959e-01" cutMax_2="1.0000000000000000e+30" cutMin_3="-1.0984969967307729e+01" cutMax_3="1.0000000000000000e+30" cutMin_4="9.9925390509817291e-01" cutMax_4="1.0000000000000000e+30" cutMin_5="3.6285526113115352e-01" cutMax_5="1.0000000000000000e+30"/>
    </Bin>
    <Bin ibin="34" effS="3.3000000000000002e-01" effB="1.6028209938667715e-04">
      <Cuts cutMin_0="1.4826835698417309e+01" cutMax_0="1.0000000000000000e+30" cutMin_1="9.8787551134102558e-01" cutMax_1="1.0000000000000000e+30" cutMin_2="6.9267253874303081e-01" cutMax_2="1.0000000000000000e+30" cutMin_3="-2.6453218316333236e+00" cutMax_3="1.0000000000000000e+30" cutMin_4="9.7241170167553348e-01" cutMax_4="1.0000000000000000e+30" cutMin_5="1.3706080942364418e-01" cutMax_5="1.0000000000000000e+30"/>
    </Bin>
    <Bin ibin="35" effS="3.4000000000000002e-01" effB="7.2855495091062039e-05">
      <Cuts cutMin_0="1.4657129090883490e+01" cutMax_0="1.0000000000000000e+30" cutMin_1="9.9935728804063373e-01" cutMax_1="1.0000000000000000e+30" cutMin_2="4.9856752573815133e-01" cutMax_2="1.0000000000000000e+30" cutMin_3="-9.9662746215808369e+00" cutMax_3="1.0000000000000000e+30" cutMin_4="9.4760455267158095e-01" cutMax_4="1.0000000000000000e+30" cutMin_5="1.1560526324116414e-01" cutMax_5="1.0000000000000000e+30"/>
    </Bin>
    <Bin ibin="36" effS="3.5000000000000003e-01" effB="1.1656880087684840e-04">
      <Cuts cutMin_0="1.4143416073124062e+01" cutMax_0="1.0000000000000000e+30" cutMin_1="9.9196170847653831e-01" cutMax_1="1.0000000000000000e+30" cutMin_2="5.7175240511486636e-01" cutMax_2="1.0000000000000000e+30" cutMin_3="-1.0279506248498043e+01" cutMax_3="1.0000000000000000e+30" cutMin_4="9.4192949586670072e-01" cutMax_4="1.0000000000000000e+30" cutMin_5="2.7417490953121137e-01" cutMax_5="1.0000000000000000e+30"/>
    </Bin>
    <Bin ibin="37" effS="3.5999999999999999e-01" effB="2.0399539789650589e-04">
      <Cuts cutMin_0="1.4696301259770504e+01" cutMax_0="1.0000000000000000e+30" cutMin_1="9.7853932440086089e-01" cutMax_1="1.0000000000000000e+30" cutMin_2="2.0797228216714583e+00" cutMax_2="1.0000000000000000e+30" cutMin_3="-8.3005577433160056e+00" cutMax_3="1.0000000000000000e+30" cutMin_4="9.8349152944767659e-01" cutMax_4="1.0000000000000000e+30" cutMin_5="5.5212732199093638e-02" cutMax_5="1.0000000000000000e+30"/>
    </Bin>
    <Bin ibin="38" effS="3.7000000000000000e-01" effB="1.4571099018212408e-04">
      <Cuts cutMin_0="1.3402996281767708e+01" cutMax_0="1.0000000000000000e+30" cutMin_1="9.9786186622950879e-01" cutMax_1="1.0000000000000000e+30" cutMin_2="3.4226310186137492e+00" cutMax_2="1.0000000000000000e+30" cutMin_3="-1.3007247873777722e+01" cutMax_3="1.0000000000000000e+30" cutMin_4="9.4359596363812392e-01" cutMax_4="1.0000000000000000e+30" cutMin_5="8.1050973692826087e-02" cutMax_5="1.0000000000000000e+30"/>
    </Bin>
    <Bin ibin="39" effS="3.8000000000000000e-01" effB="6.3141429563984275e-05">
      <Cuts cutMin_0="-7.0263326041489940e+00" cutMax_0="1.0000000000000000e+30" cutMin_1="9.9921476602651571e-01" cutMax_1="1.0000000000000000e+30" cutMin_2="4.4663284583199179e+00" cutMax_2="1.0000000000000000e+30" cutMin_3="-5.2843569381312729e+00" cutMax_3="1.0000000000000000e+30" cutMin_4="9.7335760860645959e-01" cutMax_4="1.0000000000000000e+30" cutMin_5="2.9772008921739596e-01" cutMax_5="1.0000000000000000e+30"/>
    </Bin>
    <Bin ibin="40" effS="3.9000000000000001e-01" effB="1.7971023044083267e-04">
      <Cuts cutMin_0="6.6346171614492278e+00" cutMax_0="1.0000000000000000e+30" cutMin_1="9.9881843512804103e-01" cutMax_1="1.0000000000000000e+30" cutMin_2="2.2089336262153672e+00" cutMax_2="1.0000000000000000e+30" cutMin_3="2.1187915394337651e+00" cutMax_3="1.0000000000000000e+30" cutMin_4="9.7702940671942495e-01" cutMax_4="1.0000000000000000e+30" cutMin_5="1.9649860257549343e-01" cutMax_5="1.0000000000000000e+30"/>
    </Bin>
    <Bin ibin="41" effS="4.0000000000000002e-01" effB="3.4484936622902751e-04">
      <Cuts cutMin_0="6.2254538468430951e+00" cutMax_0="1.0000000000000000e+30" cutMin_1="9.6091417478975294e-01" cutMax_1="1.0000000000000000e+30" cutMin_2="5.8406016672084016e-01" cutMax_2="1.0000000000000000e+30" cutMin_3="7.9189357446166153e-01" cutMax_3="1.0000000000000000e+30" cutMin_4="9.8915010736845710e-01" cutMax_4="1.0000000000000000e+30" cutMin_5="6.9604271420266728e-01" cutMax_5="1.0000000000000000e+30"/>
    </Bin>
    <Bin ibin="42" effS="4.1000000000000003e-01" effB="7.7712531492579728e-05">
      <Cuts cutMin_0="1.2462018760776267e+01" cutMax_0="1.0000000000000000e+30" cutMin_1="9.9730833188810086e-01" cutMax_1="1.0000000000000000e+30" cutMin_2="2.4003784310779972e+00" cutMax_2="1.0000000000000000e+30" cutMin_3="2.2291412258310110e+00" cutMax_3="1.0000000000000000e+30" cutMin_4="9.5231274779995900e-01" cutMax_4="1.0000000000000000e+30" cutMin_5="3.0944959443359599e-01" cutMax_5="1.0000000000000000e+30"/>
    </Bin>
    <Bin ibin="43" effS="4.1999999999999998e-01" effB="1.4571099018212408e-04">
      <Cuts cutMin_0="1.3140961556572149e+01" cutMax_0="1.0000000000000000e+30" cutMin_1="1.6009473066476165e-01" cutMax_1="1.0000000000000000e+30" cutMin_2="3.4289766892381235e+00" cutMax_2="1.0000000000000000e+30" cutMin_3="3.5956456953266338e+00" cutMax_3="1.0000000000000000e+30" cutMin_4="9.7223736372392144e-01" cutMax_4="1.0000000000000000e+30" cutMin_5="3.1207742311224296e-01" cutMax_5="1.0000000000000000e+30"/>
    </Bin>
    <Bin ibin="44" effS="4.2999999999999999e-01" effB="1.1171176447533071e-04">
      <Cuts cutMin_0="1.2444327623353853e+01" cutMax_0="1.0000000000000000e+30" cutMin_1="9.9335387001142084e-01" cutMax_1="1.0000000000000000e+30" cutMin_2="3.2390610959616075e+00" cutMax_2="1.0000000000000000e+30" cutMin_3="-2.1328065594868195e+00" cutMax_3="1.0000000000000000e+30" cutMin_4="9.3618831948015058e-01" cutMax_4="1.0000000000000000e+30" cutMin_5="2.2669320164136575e-01" cutMax_5="1.0000000000000000e+30"/>
    </Bin>
    <Bin ibin="45" effS="4.4000000000000000e-01" effB="2.2828056535217911e-04">
      <Cuts cutMin_0="-9.0732709729332655e+00" cutMax_0="1.0000000000000000e+30" cutMin_1="9.8709108294462966e-01" cutMax_1="1.0000000000000000e+30" cutMin_2="4.4066680712475224e+00" cutMax_2="1.0000000000000000e+30" cutMin_3="-1.4595036161347789e+01" cutMax_3="1.0000000000000000e+30" cutMin_4="9.8085850567593058e-01" cutMax_4="1.0000000000000000e+30" cutMin_5="2.1493020782073255e-01" cutMax_5="1.0000000000000000e+30"/>
    </Bin>
    <Bin ibin="46" effS="4.5000000000000001e-01" effB="1.2628285912796855e-04">
      <Cuts cutMin_0="1.1599226428050288e+01" cutMax_0="1.0000000000000000e+30" cutMin_1="9.9640141147364558e-01" cutMax_1="1.0000000000000000e+30" cutMin_2="5.5374655978278331e-01" cutMax_2="1.0000000000000000e+30" cutMin_3="-4.4615165491174142e+00" cutMax_3="1.0000000000000000e+30" cutMin_4="9.4924346943816029e-01" cutMax_4="1.0000000000000000e+30" cutMin_5="2.8946072796573968e-01" cutMax_5="1.0000000000000000e+30"/>
    </Bin>
    <Bin ibin="47" effS="4.6000000000000002e-01" effB="1.3113989552948624e-04">
      <Cuts cutMin_0="1.2569865869601582e+01" cutMax_0="1.0000000000000000e+30" cutMin_1="9.9197064546256208e-01" cutMax_1="1.0000000000000000e+30" cutMin_2="-1.7767245128733797e-01" cutMax_2="1.0000000000000000e+30" cutMin_3="-2.0439997466511528e+00" cutMax_3="1.0000000000000000e+30" cutMin_4="9.9636476960951681e-01" cutMax_4="1.0000000000000000e+30" cutMin_5="2.8934365371782811e-01" cutMax_5="1.0000000000000000e+30"/>
    </Bin>
    <Bin ibin="48" effS="4.7000000000000003e-01" effB="2.9142198036424816e-04">
      <Cuts cutMin_0="1.1628374681810438e+01" cutMax_0="1.0000000000000000e+30" cutMin_1="9.9453642573839485e-01" cutMax_1="1.0000000000000000e+30" cutMin_2="-8.5115576931847903e-02" cutMax_2="1.0000000000000000e+30" cutMin_3="2.7078622680752513e+00" cutMax_3="1.0000000000000000e+30" cutMin_4="9.1396522392030310e-01" cutMax_4="1.0000000000000000e+30" cutMin_5="1.4104202946510810e-01" cutMax_5="1.0000000000000000e+30"/>
    </Bin>
    <Bin ibin="49" effS="4.7999999999999998e-01" effB="2.3313760175369680e-04">
      <Cuts cutMin_0="9.9492774178267673e+00" cutMax_0="1.0000000000000000e+30" cutMin_1="9.9453257371017512e-01" cutMax_1="1.0000000000000000e+30" cutMin_2="4.3233813064164112e-01" cutMax_2="1.0000000000000000e+30" cutMin_3="-5.5945034732930550e+00" cutMax_3="1.0000000000000000e+30" cutMin_4="9.5697508644839124e-01" cutMax_4="1.0000000000000000e+30" cutMin_5="2.7107381876733988e-01" cutMax_5="1.0000000000000000e+30"/>
    </Bin>
    <Bin ibin="50" effS="4.8999999999999999e-01" effB="2.9627903131768107e-04">
      <Cuts cutMin_0="1.0837612781243978e+01" cutMax_0="1.0000000000000000e+30" cutMin_1="9.9561084878558748e-01" cutMax_1="1.0000000000000000e+30" cutMin_2="2.0248769589305109e+00" cutMax_2="1.0000000000000000e+30" cutMin_3="-7.0242235238726991e+00" cutMax_3="1.0000000000000000e+30" cutMin_4="9.1480122331544012e-01" cutMax_4="1.0000000000000000e+30" cutMin_5="1.1037842659513226e-01" cutMax_5="1.0000000000000000e+30"/>
    </Bin>
    <Bin ibin="51" effS="5.0000000000000000e-01" effB="2.4770869640633464e-04">
      <Cuts cutMin_0="1.2625908420411754e+01" cutMax_0="1.0000000000000000e+30" cutMin_1="9.8865712927741056e-01" cutMax_1="1.0000000000000000e+30" cutMin_2="2.1981841534352995e+00" cutMax_2="1.0000000000000000e+30" cutMin_3="-1.3879419967778077e+01" cutMax_3="1.0000000000000000e+30" cutMin_4="9.6322618815235761e-01" cutMax_4="1.0000000000000000e+30" cutMin_5="7.1055313515877253e-02" cutMax_5="1.0000000000000000e+30"/>
    </Bin>
    <Bin ibin="52" effS="5.1000000000000001e-01" effB="3.8370562833733857e-04">
      <Cuts cutMin_0="7.5960422559548739e+00" cutMax_0="1.0000000000000000e+30" cutMin_1="9.9846914646667750e-01" cutMax_1="1.0000000000000000e+30" cutMin_2="2.3674655036542029e+00" cutMax_2="1.0000000000000000e+30" cutMin_3="-1.2236111964147680e+00" cutMax_3="1.0000000000000000e+30" cutMin_4="9.2792716130370423e-01" cutMax_4="1.0000000000000000e+30" cutMin_5="7.3108468687891726e-02" cutMax_5="1.0000000000000000e+30"/>
    </Bin>
    <Bin ibin="53" effS="5.2000000000000002e-01" effB="1.5542506298515946e-04">
      <Cuts cutMin_0="1.2882346411165116e+01" cutMax_0="1.0000000000000000e+30" cutMin_1="9.9734492347435288e-01" cutMax_1="1.0000000000000000e+30" cutMin_2="1.0913374508377536e+00" cutMax_2="1.0000000000000000e+30" cutMin_3="-7.8838767269863466e+00" cutMax_3="1.0000000000000000e+30" cutMin_4="9.9751550500089892e-01" cutMax_4="1.0000000000000000e+30" cutMin_5="1.0765349412245594e-01" cutMax_5="1.0000000000000000e+30"/>
    </Bin>
    <Bin ibin="54" effS="5.3000000000000003e-01" effB="2.1856649254914373e-04">
      <Cuts cutMin_0="1.2731660788313823e+01" cutMax_0="1.0000000000000000e+30" cutMin_1="9.9392823780139961e-01" cutMax_1="1.0000000000000000e+30" cutMin_2="1.4061227773001113e+00" cutMax_2="1.0000000000000000e+30" cutMin_3="-1.2628963885817599e+01" cutMax_3="1.0000000000000000e+30" cutMin_4="9.6137728504923903e-01" cutMax_4="1.0000000000000000e+30" cutMin_5="9.1512146591073956e-02" cutMax_5="1.0000000000000000e+30"/>
    </Bin>
    <Bin ibin="55" effS="5.4000000000000004e-01" effB="3.4484936622902751e-04">
      <Cuts cutMin_0="1.2934339058410313e+01" cutMax_0="1.0000000000000000e+30" cutMin_1="9.8954518211323250e-01" cutMax_1="1.0000000000000000e+30" cutMin_2="5.1172313428636373e-02" cutMax_2="1.0000000000000000e+30" cutMin_3="-7.7407364817724345e+00" cutMax_3="1.0000000000000000e+30" cutMin_4="9.8701231526001409e-01" cutMax_4="1.0000000000000000e+30" cutMin_5="7.6216042672982792e-02" cutMax_5="1.0000000000000000e+30"/>
    </Bin>
    <Bin ibin="56" effS="5.5000000000000004e-01" effB="3.9341970114037395e-04">
      <Cuts cutMin_0="7.0736285767152927e+00" cutMax_0="1.0000000000000000e+30" cutMin_1="9.9691281217201222e-01" cutMax_1="1.0000000000000000e+30" cutMin_2="-1.9319803163775653e-01" cutMax_2="1.0000000000000000e+30" cutMin_3="2.7207164982676444e+00" cutMax_3="1.0000000000000000e+30" cutMin_4="9.9535142435423019e-01" cutMax_4="1.0000000000000000e+30" cutMin_5="1.1282587294800082e-01" cutMax_5="1.0000000000000000e+30"/>
    </Bin>
    <Bin ibin="57" effS="5.6000000000000005e-01" effB="5.1970256026834249e-04">
      <Cuts cutMin_0="9.0498482328397873e+00" cutMax_0="1.0000000000000000e+30" cutMin_1="9.8616399246398423e-01" cutMax_1="1.0000000000000000e+30" cutMin_2="3.7664949314408314e-01" cutMax_2="1.0000000000000000e+30" cutMin_3="1.5267952248025800e+00" cutMax_3="1.0000000000000000e+30" cutMin_4="9.8133424622263388e-01" cutMax_4="1.0000000000000000e+30" cutMin_5="1.1010256374001055e-01" cutMax_5="1.0000000000000000e+30"/>
    </Bin>
    <Bin ibin="58" effS="5.7000000000000006e-01" effB="6.7027058685198426e-04">
      <Cuts cutMin_0="6.3284173607710912e+00" cutMax_0="1.0000000000000000e+30" cutMin_1="9.8754144131549981e-01" cutMax_1="1.0000000000000000e+30" cutMin_2="6.5068330418799081e-01" cutMax_2="1.0000000000000000e+30" cutMin_3="-3.8349164510095068e+00" cutMax_3="1.0000000000000000e+30" cutMin_4="9.9603114787382052e-01" cutMax_4="1.0000000000000000e+30" cutMin_5="3.0038249340011097e-01" cutMax_5="1.0000000000000000e+30"/>
    </Bin>
    <Bin ibin="59" effS="5.7999999999999996e-01" effB="6.2655727379024029e-04">
      <Cuts cutMin_0="7.6481985057541868e+00" cutMax_0="1.0000000000000000e+30" cutMin_1="-3.3676828773973946e-02" cutMax_1="1.0000000000000000e+30" cutMin_2="1.6105167843216912e+00" cutMax_2="1.0000000000000000e+30" cutMin_3="2.7287103539944519e+00" cutMax_3="1.0000000000000000e+30" cutMin_4="9.9601874904076682e-01" cutMax_4="1.0000000000000000e+30" cutMin_5="2.8990012107441693e-01" cutMax_5="1.0000000000000000e+30"/>
    </Bin>
    <Bin ibin="60" effS="5.8999999999999997e-01" effB="9.2283630510792136e-04">
      <Cuts cutMin_0="7.0827913770064548e+00" cutMax_0="1.0000000000000000e+30" cutMin_1="9.5009977456519401e-01" cutMax_1="1.0000000000000000e+30" cutMin_2="7.8116976445240616e-01" cutMax_2="1.0000000000000000e+30" cutMin_3="1.9173971931512874e+00" cutMax_3="1.0000000000000000e+30" cutMin_4="9.1593563212495743e-01" cutMax_4="1.0000000000000000e+30" cutMin_5="3.0127021493290429e-01" cutMax_5="1.0000000000000000e+30"/>
    </Bin>
    <Bin ibin="61" effS="5.9999999999999998e-01" effB="5.2941660396754742e-04">
      <Cuts cutMin_0="7.6439770311342681e+00" cutMax_0="1.0000000000000000e+30" cutMin_1="9.8518823524839516e-01" cutMax_1="1.0000000000000000e+30" cutMin_2="2.8670690745647698e-01" cutMax_2="1.0000000000000000e+30" cutMin_3="1.1159426919268454e+00" cutMax_3="1.0000000000000000e+30" cutMin_4="9.6753888857639980e-01" cutMax_4="1.0000000000000000e+30" cutMin_5="2.6290223846269972e-01" cutMax_5="1.0000000000000000e+30"/>
    </Bin>
    <Bin ibin="62" effS="6.0999999999999999e-01" effB="9.8597770556807518e-04">
      <Cuts cutMin_0="7.7852082108060543e+00" cutMax_0="1.0000000000000000e+30" cutMin_1="9.8291563471537680e-01" cutMax_1="1.0000000000000000e+30" cutMin_2="-1.3659346951265372e-01" cutMax_2="1.0000000000000000e+30" cutMin_3="6.6210486442913119e-01" cutMax_3="1.0000000000000000e+30" cutMin_4="9.1278837509289656e-01" cutMax_4="1.0000000000000000e+30" cutMin_5="2.2023037018373967e-01" cutMax_5="1.0000000000000000e+30"/>
    </Bin>
    <Bin ibin="63" effS="6.2000000000000000e-01" effB="1.1656879214569926e-03">
      <Cuts cutMin_0="6.6968431669452437e+00" cutMax_0="1.0000000000000000e+30" cutMin_1="9.3631363108855137e-01" cutMax_1="1.0000000000000000e+30" cutMin_2="8.6517146550406199e-01" cutMax_2="1.0000000000000000e+30" cutMin_3="3.2277894550133901e+00" cutMax_3="1.0000000000000000e+30" cutMin_4="9.7742840403767439e-01" cutMax_4="1.0000000000000000e+30" cutMin_5="1.3299365246152317e-01" cutMax_5="1.0000000000000000e+30"/>
    </Bin>
    <Bin ibin="64" effS="6.3000000000000000e-01" effB="8.0626748967915773e-04">
      <Cuts cutMin_0="7.1744864785923497e+00" cutMax_0="1.0000000000000000e+30" cutMin_1="9.8109251416892440e-01" cutMax_1="1.0000000000000000e+30" cutMin_2="-1.6947359145508142e-01" cutMax_2="1.0000000000000000e+30" cutMin_3="2.4619407779165114e+00" cutMax_3="1.0000000000000000e+30" cutMin_4="9.6609358076825191e-01" cutMax_4="1.0000000000000000e+30" cutMin_5="1.6079246910606487e-01" cutMax_5="1.0000000000000000e+30"/>
    </Bin>
    <Bin ibin="65" effS="6.4000000000000001e-01" effB="9.5683557447046041e-04">
      <Cuts cutMin_0="7.4427064696921210e+00" cutMax_0="1.0000000000000000e+30" cutMin_1="9.5008752048448486e-01" cutMax_1="1.0000000000000000e+30" cutMin_2="2.4013097771570693e+00" cutMax_2="1.0000000000000000e+30" cutMin_3="-3.2153569647066886e+00" cutMax_3="1.0000000000000000e+30" cutMin_4="9.7521874819161181e-01" cutMax_4="1.0000000000000000e+30" cutMin_5="1.1003610936152142e-01" cutMax_5="1.0000000000000000e+30"/>
    </Bin>
    <Bin ibin="66" effS="6.5000000000000002e-01" effB="7.2369794361293316e-04">
      <Cuts cutMin_0="7.7638185578746661e+00" cutMax_0="1.0000000000000000e+30" cutMin_1="9.7907469387961510e-01" cutMax_1="1.0000000000000000e+30" cutMin_2="2.1629311878596731e+00" cutMax_2="1.0000000000000000e+30" cutMin_3="-1.3045701332608139e+00" cutMax_3="1.0000000000000000e+30" cutMin_4="9.8416210314163255e-01" cutMax_4="1.0000000000000000e+30" cutMin_5="9.5278232365386767e-02" cutMax_5="1.0000000000000000e+30"/>
    </Bin>
    <Bin ibin="67" effS="6.6000000000000003e-01" effB="1.2434005038812757e-03">
      <Cuts cutMin_0="5.4511964185855124e+00" cutMax_0="1.0000000000000000e+30" cutMin_1="9.8314651846638501e-01" cutMax_1="1.0000000000000000e+30" cutMin_2="2.1947657602140742e+00" cutMax_2="1.0000000000000000e+30" cutMin_3="-1.0564113619591865e+01" cutMax_3="1.0000000000000000e+30" cutMin_4="9.8303818945406696e-01" cutMax_4="1.0000000000000000e+30" cutMin_5="1.0915420786825349e-01" cutMax_5="1.0000000000000000e+30"/>
    </Bin>
    <Bin ibin="68" effS="6.7000000000000004e-01" effB="1.0976894991472363e-03">
      <Cuts cutMin_0="5.7108570887738379e+00" cutMax_0="1.0000000000000000e+30" cutMin_1="9.7925158668048284e-01" cutMax_1="1.0000000000000000e+30" cutMin_2="9.6721921314133463e-01" cutMax_2="1.0000000000000000e+30" cutMin_3="-4.4167705155176371e+00" cutMax_3="1.0000000000000000e+30" cutMin_4="9.7772614613983388e-01" cutMax_4="1.0000000000000000e+30" cutMin_5="3.0712580480082985e-01" cutMax_5="1.0000000000000000e+30"/>
    </Bin>
    <Bin ibin="69" effS="6.8000000000000005e-01" effB="1.0345480404794216e-03">
      <Cuts cutMin_0="6.7009059945439251e+00" cutMax_0="1.0000000000000000e+30" cutMin_1="9.7832685993964941e-01" cutMax_1="1.0000000000000000e+30" cutMin_2="1.1831824183258624e+00" cutMax_2="1.0000000000000000e+30" cutMin_3="-4.8461157567205611e+00" cutMax_3="1.0000000000000000e+30" cutMin_4="9.1182166758421113e-01" cutMax_4="1.0000000000000000e+30" cutMin_5="2.6369904302706715e-01" cutMax_5="1.0000000000000000e+30"/>
    </Bin>
    <Bin ibin="70" effS="6.9000000000000006e-01" effB="9.0340815950185061e-04">
      <Cuts cutMin_0="4.9514257227698257e+00" cutMax_0="1.0000000000000000e+30" cutMin_1="9.8693338004040720e-01" cutMax_1="1.0000000000000000e+30" cutMin_2="1.2205554521136672e+00" cutMax_2="1.0000000000000000e+30" cutMin_3="1.1881219098143116e+00" cutMax_3="1.0000000000000000e+30" cutMin_4="9.6345865524459218e-01" cutMax_4="1.0000000000000000e+30" cutMin_5="2.9712654375884245e-01" cutMax_5="1.0000000000000000e+30"/>
    </Bin>
    <Bin ibin="71" effS="7.0000000000000007e-01" effB="1.1948301689699292e-03">
      <Cuts cutMin_0="6.6674302215072307e+00" cutMax_0="1.0000000000000000e+30" cutMin_1="8.2869326655939568e-01" cutMax_1="1.0000000000000000e+30" cutMin_2="4.6050689398887623e-01" cutMax_2="1.0000000000000000e+30" cutMin_3="2.8876028226724708e+00" cutMax_3="1.0000000000000000e+30" cutMin_4="9.8089065655328400e-01" cutMax_4="1.0000000000000000e+30" cutMin_5="2.5438729227830431e-01" cutMax_5="1.0000000000000000e+30"/>
    </Bin>
    <Bin ibin="72" effS="7.0999999999999996e-01" effB="1.2725427513942122e-03">
      <Cuts cutMin_0="6.6988002507451156e+00" cutMax_0="1.0000000000000000e+30" cutMin_1="9.8027917150796484e-01" cutMax_1="1.0000000000000000e+30" cutMin_2="9.9106981873202793e-01" cutMax_2="1.0000000000000000e+30" cutMin_3="-1.5340659649299464e+01" cutMax_3="1.0000000000000000e+30" cutMin_4="9.6936843389261174e-01" cutMax_4="1.0000000000000000e+30" cutMin_5="1.4466742263142840e-01" cutMax_5="1.0000000000000000e+30"/>
    </Bin>
    <Bin ibin="73" effS="7.1999999999999997e-01" effB="1.3793974649161100e-03">
      <Cuts cutMin_0="6.5307539622415298e+00" cutMax_0="1.0000000000000000e+30" cutMin_1="9.7181716593787715e-01" cutMax_1="1.0000000000000000e+30" cutMin_2="2.1372657238157652e-01" cutMax_2="1.0000000000000000e+30" cutMin_3="1.9610028912978894e+00" cutMax_3="1.0000000000000000e+30" cutMin_4="9.4439833642234072e-01" cutMax_4="1.0000000000000000e+30" cutMin_5="1.5211864546073040e-01" cutMax_5="1.0000000000000000e+30"/>
    </Bin>
    <Bin ibin="74" effS="7.2999999999999998e-01" effB="1.4716810546815395e-03">
      <Cuts cutMin_0="6.5515274414899167e+00" cutMax_0="1.0000000000000000e+30" cutMin_1="9.8562060097935467e-01" cutMax_1="1.0000000000000000e+30" cutMin_2="5.3464869785324998e-01" cutMax_2="1.0000000000000000e+30" cutMin_3="-1.0631063650639801e+01" cutMax_3="1.0000000000000000e+30" cutMin_4="9.7081141206591426e-01" cutMax_4="1.0000000000000000e+30" cutMin_5="1.4046981237849457e-01" cutMax_5="1.0000000000000000e+30"/>
    </Bin>
    <Bin ibin="75" effS="7.3999999999999999e-01" effB="2.5547994300723076e-03">
      <Cuts cutMin_0="5.4111574650958936e+00" cutMax_0="1.0000000000000000e+30" cutMin_1="9.3843469387901346e-01" cutMax_1="1.0000000000000000e+30" cutMin_2="8.3500577383735664e-01" cutMax_2="1.0000000000000000e+30" cutMin_3="-5.3001890259861169e+00" cutMax_3="1.0000000000000000e+30" cutMin_4="9.9448047762816716e-01" cutMax_4="1.0000000000000000e+30" cutMin_5="2.5361767841208782e-01" cutMax_5="1.0000000000000000e+30"/>
    </Bin>
    <Bin ibin="76" effS="7.5000000000000000e-01" effB="2.9627901967614889e-03">
      <Cuts cutMin_0="5.3976947542856202e+00" cutMax_0="1.0000000000000000e+30" cutMin_1="9.0359699050932718e-01" cutMax_1="1.0000000000000000e+30" cutMin_2="9.1300563883994768e-03" cutMax_2="1.0000000000000000e+30" cutMin_3="1.7598357319062909e+00" cutMax_3="1.0000000000000000e+30" cutMin_4="9.2349755437319914e-01" cutMax_4="1.0000000000000000e+30" cutMin_5="2.8283672560142292e-01" cutMax_5="1.0000000000000000e+30"/>
    </Bin>
    <Bin ibin="77" effS="7.6000000000000001e-01" effB="3.5553483758121729e-03">
      <Cuts cutMin_0="5.3819204270788550e+00" cutMax_0="1.0000000000000000e+30" cutMin_1="9.7317389476290239e-01" cutMax_1="1.0000000000000000e+30" cutMin_2="3.0276321802973427e-01" cutMax_2="1.0000000000000000e+30" cutMin_3="-9.6357365077086321e+00" cutMax_3="1.0000000000000000e+30" cutMin_4="9.9873599756744391e-01" cutMax_4="1.0000000000000000e+30" cutMin_5="1.4257389363678311e-01" cutMax_5="1.0000000000000000e+30"/>
    </Bin>
    <Bin ibin="78" effS="7.7000000000000002e-01" effB="2.6033697649836540e-03">
      <Cuts cutMin_0="6.3607592525066581e+00" cutMax_0="1.0000000000000000e+30" cutMin_1="9.4861057480176036e-01" cutMax_1="1.0000000000000000e+30" cutMin_2="1.1822011324289770e+00" cutMax_2="1.0000000000000000e+30" cutMin_3="-6.3438356916410577e+00" cutMax_3="1.0000000000000000e+30" cutMin_4="9.5440882893333678e-01" cutMax_4="1.0000000000000000e+30" cutMin_5="1.0911787193687247e-01" cutMax_5="1.0000000000000000e+30"/>
    </Bin>
    <Bin ibin="79" effS="7.8000000000000003e-01" effB="1.6271061031147838e-03">
      <Cuts cutMin_0="6.5497739664270362e+00" cutMax_0="1.0000000000000000e+30" cutMin_1="9.5642879929466929e-01" cutMax_1="1.0000000000000000e+30" cutMin_2="1.2494103040083986e+00" cutMax_2="1.0000000000000000e+30" cutMin_3="1.4316463543744584e+00" cutMax_3="1.0000000000000000e+30" cutMin_4="9.9070244990079603e-01" cutMax_4="1.0000000000000000e+30" cutMin_5="7.0220049276840335e-02" cutMax_5="1.0000000000000000e+30"/>
    </Bin>
    <Bin ibin="80" effS="7.9000000000000004e-01" effB="1.8748148577287793e-03">
      <Cuts cutMin_0="6.1977297339865149e+00" cutMax_0="1.0000000000000000e+30" cutMin_1="9.6173533845862402e-01" cutMax_1="1.0000000000000000e+30" cutMin_2="-2.7859193484362266e-01" cutMax_2="1.0000000000000000e+30" cutMin_3="2.7101503841868784e+00" cutMax_3="1.0000000000000000e+30" cutMin_4="9.9158538391585072e-01" cutMax_4="1.0000000000000000e+30" cutMin_5="8.1319838000569175e-02" cutMax_5="1.0000000000000000e+30"/>
    </Bin>
    <Bin ibin="81" effS="8.0000000000000004e-01" effB="2.7490807697176933e-03">
      <Cuts cutMin_0="6.0457934617665545e+00" cutMax_0="1.0000000000000000e+30" cutMin_1="9.8518859348105459e-01" cutMax_1="1.0000000000000000e+30" cutMin_2="-3.1621815391193359e-01" cutMax_2="1.0000000000000000e+30" cutMin_3="-1.6945693488424305e+00" cutMax_3="1.0000000000000000e+30" cutMin_4="9.9650897791789717e-01" cutMax_4="1.0000000000000000e+30" cutMin_5="1.0671377521484993e-01" cutMax_5="1.0000000000000000e+30"/>
    </Bin>
    <Bin ibin="82" effS="8.1000000000000005e-01" effB="3.8710555527359247e-03">
      <Cuts cutMin_0="5.1049961920100380e+00" cutMax_0="1.0000000000000000e+30" cutMin_1="8.3698524772523164e-01" cutMax_1="1.0000000000000000e+30" cutMin_2="7.9702938725248784e-01" cutMax_2="1.0000000000000000e+30" cutMin_3="2.3898954878166201e+00" cutMax_3="1.0000000000000000e+30" cutMin_4="9.9278445226833634e-01" cutMax_4="1.0000000000000000e+30" cutMin_5="9.4251778028883001e-02" cutMax_5="1.0000000000000000e+30"/>
    </Bin>
    <Bin ibin="83" effS="8.2000000000000006e-01" effB="5.7215853594243526e-03">
      <Cuts cutMin_0="5.2687779283048135e+00" cutMax_0="1.0000000000000000e+30" cutMin_1="-2.3509383834235556e-01" cutMax_1="1.0000000000000000e+30" cutMin_2="3.3054419750004693e-01" cutMax_2="1.0000000000000000e+30" cutMin_3="2.3348010155368017e+00" cutMax_3="1.0000000000000000e+30" cutMin_4="9.5364436953526988e-01" cutMax_4="1.0000000000000000e+30" cutMin_5="1.1469657324892125e-01" cutMax_5="1.0000000000000000e+30"/>
    </Bin>
    <Bin ibin="84" effS="8.3000000000000007e-01" effB="4.3421876616775990e-03">
      <Cuts cutMin_0="5.3719872837605136e+00" cutMax_0="1.0000000000000000e+30" cutMin_1="9.7911624704679723e-01" cutMax_1="1.0000000000000000e+30" cutMin_2="4.2997019497761507e-01" cutMax_2="1.0000000000000000e+30" cutMin_3="-9.1473210683379804e+00" cutMax_3="1.0000000000000000e+30" cutMin_4="9.5112698976485888e-01" cutMax_4="1.0000000000000000e+30" cutMin_5="1.0357970297373652e-01" cutMax_5="1.0000000000000000e+30"/>
    </Bin>
    <Bin ibin="85" effS="8.3999999999999997e-01" effB="7.9266782850027084e-03">
      <Cuts cutMin_0="5.1077590257084742e+00" cutMax_0="1.0000000000000000e+30" cutMin_1="9.1152200877647283e-01" cutMax_1="1.0000000000000000e+30" cutMin_2="2.9576753490349994e-01" cutMax_2="1.0000000000000000e+30" cutMin_3="-1.5375285135008115e+01" cutMax_3="1.0000000000000000e+30" cutMin_4="9.9651777140007081e-01" cutMax_4="1.0000000000000000e+30" cutMin_5="1.1111565338907033e-01" cutMax_5="1.0000000000000000e+30"/>
    </Bin>
    <Bin ibin="86" effS="8.4999999999999998e-01" effB="8.1063881516456604e-03">
      <Cuts cutMin_0="5.2165636691732962e+00" cutMax_0="1.0000000000000000e+30" cutMin_1="7.6721744020074778e-01" cutMax_1="1.0000000000000000e+30" cutMin_2="3.5236252592818074e-01" cutMax_2="1.0000000000000000e+30" cutMin_3="1.3893561739516800e+00" cutMax_3="1.0000000000000000e+30" cutMin_4="8.9565001104497843e-01" cutMax_4="1.0000000000000000e+30" cutMin_5="1.0310612063295355e-01" cutMax_5="1.0000000000000000e+30"/>
    </Bin>
    <Bin ibin="87" effS="8.5999999999999999e-01" effB="1.4546814374625683e-02">
      <Cuts cutMin_0="2.6373143700544386e+00" cutMax_0="1.0000000000000000e+30" cutMin_1="9.7759049229768846e-01" cutMax_1="1.0000000000000000e+30" cutMin_2="8.4677309611047580e-01" cutMax_2="1.0000000000000000e+30" cutMin_3="-1.2742865436311909e+01" cutMax_3="1.0000000000000000e+30" cutMin_4="9.7069367433493670e-01" cutMax_4="1.0000000000000000e+30" cutMin_5="2.2832981226132032e-01" cutMax_5="1.0000000000000000e+30"/>
    </Bin>
    <Bin ibin="88" effS="8.7000000000000000e-01" effB="2.1672083064913750e-02">
      <Cuts cutMin_0="2.5992018373324219e+00" cutMax_0="1.0000000000000000e+30" cutMin_1="9.7274487278019872e-01" cutMax_1="1.0000000000000000e+30" cutMin_2="8.7702636761575237e-01" cutMax_2="1.0000000000000000e+30" cutMin_3="-5.7342213426278947e+00" cutMax_3="1.0000000000000000e+30" cutMin_4="8.7125144939241994e-01" cutMax_4="1.0000000000000000e+30" cutMin_5="1.9055002218199912e-01" cutMax_5="1.0000000000000000e+30"/>
    </Bin>
    <Bin ibin="89" effS="8.8000000000000000e-01" effB="2.2507492452859879e-02">
      <Cuts cutMin_0="2.6653099906272675e+00" cutMax_0="1.0000000000000000e+30" cutMin_1="-2.6077822677607093e-01" cutMax_1="1.0000000000000000e+30" cutMin_2="8.5363891443601114e-01" cutMax_2="1.0000000000000000e+30" cutMin_3="1.0775346918457183e+00" cutMax_3="1.0000000000000000e+30" cutMin_4="9.8614389729114571e-01" cutMax_4="1.0000000000000000e+30" cutMin_5="2.8948393647022913e-01" cutMax_5="1.0000000000000000e+30"/>
    </Bin>
    <Bin ibin="90" effS="8.9000000000000001e-01" effB="2.7505379170179367e-02">
      <Cuts cutMin_0="2.7623374424264417e+00" cutMax_0="1.0000000000000000e+30" cutMin_1="-2.5824852556924649e-01" cutMax_1="1.0000000000000000e+30" cutMin_2="4.8530224696034413e-01" cutMax_2="1.0000000000000000e+30" cutMin_3="1.1144503398249308e+00" cutMax_3="1.0000000000000000e+30" cutMin_4="9.9415333305180176e-01" cutMax_4="1.0000000000000000e+30" cutMin_5="2.8789735631685576e-01" cutMax_5="1.0000000000000000e+30"/>
    </Bin>
    <Bin ibin="91" effS="9.0000000000000002e-01" effB="2.9341338202357292e-02">
      <Cuts cutMin_0="2.7575305265858181e+00" cutMax_0="1.0000000000000000e+30" cutMin_1="-2.5088150180057139e-01" cutMax_1="1.0000000000000000e+30" cutMin_2="4.8373151389752245e-01" cutMax_2="1.0000000000000000e+30" cutMin_3="1.1355132004789961e+00" cutMax_3="1.0000000000000000e+30" cutMin_4="9.6572752508571535e-01" cutMax_4="1.0000000000000000e+30" cutMin_5="2.8789934123344840e-01" cutMax_5="1.0000000000000000e+30"/>
    </Bin>
    <Bin ibin="92" effS="9.1000000000000003e-01" effB="3.2406125217676163e-02">
      <Cuts cutMin_0="2.6509586579117053e+00" cutMax_0="1.0000000000000000e+30" cutMin_1="9.3823005597574227e-01" cutMax_1="1.0000000000000000e+30" cutMin_2="7.9216764384380922e-01" cutMax_2="1.0000000000000000e+30" cutMin_3="-1.3091483971016102e+01" cutMax_3="1.0000000000000000e+30" cutMin_4="9.5842479717776874e-01" cutMax_4="1.0000000000000000e+30" cutMin_5="1.4244767179243573e-01" cutMax_5="1.0000000000000000e+30"/>
    </Bin>
    <Bin ibin="93" effS="9.2000000000000004e-01" effB="1.9632128998637199e-02">
      <Cuts cutMin_0="-1.0592756506127374e+00" cutMax_0="1.0000000000000000e+30" cutMin_1="9.8582292022876061e-01" cutMax_1="1.0000000000000000e+30" cutMin_2="6.6580819289725823e-01" cutMax_2="1.0000000000000000e+30" cutMin_3="1.5989834062429500e+00" cutMax_3="1.0000000000000000e+30" cutMin_4="9.1617289553943582e-01" cutMax_4="1.0000000000000000e+30" cutMin_5="8.8034231805478966e-02" cutMax_5="1.0000000000000000e+30"/>
    </Bin>
    <Bin ibin="94" effS="9.3000000000000005e-01" effB="2.7354810386896133e-02">
      <Cuts cutMin_0="-4.4763249211313587e+00" cutMax_0="1.0000000000000000e+30" cutMin_1="9.5520861042179628e-01" cutMax_1="1.0000000000000000e+30" cutMin_2="3.9911536721904195e-01" cutMax_2="1.0000000000000000e+30" cutMin_3="1.8425464367445137e+00" cutMax_3="1.0000000000000000e+30" cutMin_4="9.6492449755375564e-01" cutMax_4="1.0000000000000000e+30" cutMin_5="1.0706772056209529e-01" cutMax_5="1.0000000000000000e+30"/>
    </Bin>
    <Bin ibin="95" effS="9.4000000000000006e-01" effB="3.3668953925371170e-02">
      <Cuts cutMin_0="7.2359219852167334e-01" cutMax_0="1.0000000000000000e+30" cutMin_1="8.7500374782465784e-01" cutMax_1="1.0000000000000000e+30" cutMin_2="7.7767971758681009e-01" cutMax_2="1.0000000000000000e+30" cutMin_3="1.7357798534512867e+00" cutMax_3="1.0000000000000000e+30" cutMin_4="9.9902171694965758e-01" cutMax_4="1.0000000000000000e+30" cutMin_5="7.8344483178992383e-02" cutMax_5="1.0000000000000000e+30"/>
    </Bin>
    <Bin ibin="96" effS="9.5000000000000007e-01" effB="4.3655015528202057e-02">
      <Cuts cutMin_0="-6.5241855713122003e+00" cutMax_0="1.0000000000000000e+30" cutMin_1="9.6101471068195499e-01" cutMax_1="1.0000000000000000e+30" cutMin_2="6.6216034960961445e-01" cutMax_2="1.0000000000000000e+30" cutMin_3="9.9937559858263070e-01" cutMax_3="1.0000000000000000e+30" cutMin_4="9.7932472744689192e-01" cutMax_4="1.0000000000000000e+30" cutMin_5="7.2128646378181033e-02" cutMax_5="1.0000000000000000e+30"/>
    </Bin>
    <Bin ibin="97" effS="9.5999999999999996e-01" effB="3.6131471395492554e-02">
      <Cuts cutMin_0="2.7809012402605688e+00" cutMax_0="1.0000000000000000e+30" cutMin_1="8.6969463164512562e-01" cutMax_1="1.0000000000000000e+30" cutMin_2="3.9727720660107640e-01" cutMax_2="1.0000000000000000e+30" cutMin_3="1.0374691819553643e+00" cutMax_3="1.0000000000000000e+30" cutMin_4="9.8373727416356704e-01" cutMax_4="1.0000000000000000e+30" cutMin_5="1.0299885982844507e-01" cutMax_5="1.0000000000000000e+30"/>
    </Bin>
    <Bin ibin="98" effS="9.6999999999999997e-01" effB="4.0789365768432617e-02">
      <Cuts cutMin_0="2.6890776211716934e+00" cutMax_0="1.0000000000000000e+30" cutMin_1="9.7574911000430609e-01" cutMax_1="1.0000000000000000e+30" cutMin_2="5.8026978926466299e-02" cutMax_2="1.0000000000000000e+30" cutMin_3="-1.0525037585124585e+01" cutMax_3="1.0000000000000000e+30" cutMin_4="9.7255800358153133e-01" cutMax_4="1.0000000000000000e+30" cutMin_5="1.0022657759101222e-01" cutMax_5="1.0000000000000000e+30"/>
    </Bin>
    <Bin ibin="99" effS="9.7999999999999998e-01" effB="4.3465591967105865e-02">
      <Cuts cutMin_0="2.6945473728297520e+00" cutMax_0="1.0000000000000000e+30" cutMin_1="9.0061722161653079e-01" cutMax_1="1.0000000000000000e+30" cutMin_2="7.9322726977693681e-01" cutMax_2="1.0000000000000000e+30" cutMin_3="-8.5514331590552697e+00" cutMax_3="1.0000000000000000e+30" cutMin_4="9.6132454347563445e-01" cutMax_4="1.0000000000000000e+30" cutMin_5="9.7837642459449398e-02" cutMax_5="1.0000000000000000e+30"/>
    </Bin>
    <Bin ibin="100" effS="9.8999999999999999e-01" effB="5.4194778203964233e-02">
      <Cuts cutMin_0="2.7063123807823883e+00" cutMax_0="1.0000000000000000e+30" cutMin_1="9.1264783999860821e-01" cutMax_1="1.0000000000000000e+30" cutMin_2="3.5633875888179789e-01" cutMax_2="1.0000000000000000e+30" cutMin_3="-4.3907560434703274e+00" cutMax_3="1.0000000000000000e+30" cutMin_4="9.9135348589239913e-01" cutMax_4="1.0000000000000000e+30" cutMin_5="9.7378669928115849e-02" cutMax_5="1.0000000000000000e+30"/>
    </Bin>
  </Weights>
</MethodSetup>
